ja_sentence_segmenter/__init__.py
ja_sentence_segmenter/common/__init__.py
ja_sentence_segmenter/common/pipeline.py
ja_sentence_segmenter/concatenate/__init__.py
ja_sentence_segmenter/concatenate/simple_concatenator.py
ja_sentence_segmenter/normalize/__init__.py
ja_sentence_segmenter/normalize/neologd_normalizer.py
ja_sentence_segmenter/py.typed
ja_sentence_segmenter/split/__init__.py
ja_sentence_segmenter/split/simple_splitter.py
ja_sentence_segmenter-0.0.2.dist-info/LICENSE
ja_sentence_segmenter-0.0.2.dist-info/WHEEL
ja_sentence_segmenter-0.0.2.dist-info/METADATA
ja_sentence_segmenter-0.0.2.dist-info/RECORD
