Metadata-Version: 2.1
Name: ja-sentence-segmenter
Version: 0.0.2
Summary: sentence segmenter for japanese text
Home-page: https://github.com/wwwcojp
License: MIT
Author: wwwcojp
Requires-Python: >=3.6,<4.0
Classifier: Development Status :: 3 - Alpha
Classifier: Environment :: Console
Classifier: License :: OSI Approved :: MIT License
Classifier: Programming Language :: Python :: 3
Classifier: Programming Language :: Python :: 3.6
Classifier: Programming Language :: Python :: 3.7
Classifier: Programming Language :: Python :: 3.8
Classifier: Topic :: Text Processing
Classifier: Topic :: Text Processing :: General
Project-URL: Repository, https://github.com/wwwcojp/ja_sentence_segmenter
